scrapelo/__init__.py
scrapelo/get_club_elo.py
scrapelo/get_competition_elo.py
scrapelo-0.0.5.dist-info/METADATA
scrapelo-0.0.5.dist-info/WHEEL
scrapelo-0.0.5.dist-info/top_level.txt
scrapelo-0.0.5.dist-info/RECORD
